donkeykong/__init__.py
donkeykong/invalidation.py
donkeykong/monkey_patching/__init__.py
donkeykong/monkey_patching/dependencies.py
donkeykong/monkey_patching/target.py
donkeykong/scripts/__init__.py
donkeykong/scripts/invalidate.py
donkeykong/scripts/main.py
donkeykong/scripts/run.py
donkeykong/scripts/server.py
donkeykong/target/__init__.py
donkeykong/target/local_target.py
donkeykong/target/numpy.py
donkeykong/target/pandas.py
donkeykong/target/tifffile.py
donkeykong-0.0.1.dist-info/LICENSE
donkeykong-0.0.1.dist-info/METADATA
donkeykong-0.0.1.dist-info/WHEEL
donkeykong-0.0.1.dist-info/entry_points.txt
donkeykong-0.0.1.dist-info/top_level.txt
donkeykong-0.0.1.dist-info/RECORD
